[
    {
        "company": "Amazon",
        "position": "Events Support Engineer",
        "url": "https://www.amazon.jobs/en-gb/jobs/2731066/events-support-engineer-it-services"
    },
    {
        "company": "Amazon",
        "position": "Transaction Risk Investigator",
        "url": "https://www.amazon.jobs/en-gb/jobs/2698922/transaction-risk-investigator"
    },
    {
        "company": "Amazon",
        "position": "Manager Investigations,KYC",
        "url": "https://amazon.jobs/en-gb/jobs/2706087/manager-investigations-kyc"
    }
]
